{
  "tab_home": "Home",
  "tab_promotions": "Promotions & News",
  "tab_pizza": "Pizza",
  "tab_drinks": "Drinks",
  "tab_sides": "Sides",
  "tab_starter": "Desserts",

  "drawer_sign_in": "Sign In",
  "drawer_home": "HOME",
  "drawer_pizza_maker": "PIZZA MAKER",
  "drawer_pizza_tracker": "PIZZA TRACKER",
  "drawer_pizzerias": "PIZZERIAS",
  "drawer_career": "CAREERS",
  "drawer_franchising": "FRANCHISING",
  "drawer_club": "DOMINO'S CLUB",
  "drawer_leave_review": "LEAVE A REVIEW",
  "drawer_news": "NEWS",
  "drawer_call_us": "Call us:",
  "drawer_working_hours": "Open daily from 10:00 to 22:00",
  "drawer_useful_info": "Useful Information",
  "drawer_allergens_info": "Allergens & Nutritional Information",
  "drawer_food_safety_policy": "Food Safety Policy",
  "drawer_privacy_policy": "Privacy Policy",
  "drawer_information_policy": "Information Policy",
  "drawer_public_offer": "Public Offer",
  "drawer_follow_us": "Follow us",
  "drawer_payment_support": "Payment Support",

  "location_title": "Where are you located?",

  "pizzaDough": "Dough",
  "pizzaCrust": "Crust",

  "filter_title": "Filter",
  "filter_clear": "Clear",
  "filter_apply": "Apply",

  "sort_default": "Sort",
  "sort_price_asc": "Price Low to High",
  "sort_price_desc": "Price High to Low",

  "starters_weight_unit": "g*",
  "add_to_cart": "Add to Cart",
  "replace_ingredients": " Replace Ingredients",
  "currency": "UAH",
  "price_title": "Price",

  "sign_in_email_placeholder": "Email",
  "sign_in_password_placeholder": "Password",
  "sign_in_login_button": "Login",
  "sign_in_signup_button": "Sign Up",
  "sign_in_email_required": "Email is required",
  "sign_in_email_invalid": "Please enter a valid email",
  "sign_in_password_required": "Password is required",
  "sign_in_password_min_length": "Password must be at least 6 characters",
  "sign_in_error_user_not_found": "User not found",
  "sign_in_error_invalid_credential": "Wrong email or password",
  "sign_in_error_default": "An error occurred during sign-in",

  "sign_up_username_placeholder": "User Name",
  "sign_up_email_placeholder": "Email",
  "sign_up_password_placeholder": "Password",
  "sign_up_create_account_button": "Create New Account",
  "sign_up_goto_signin_button": "Go To Sign In",
  "sign_up_username_required": "User name is required",
  "sign_up_username_min_length": "User name must be more than 5 characters",
  "sign_up_email_invalid": "Email is wrong",
  "sign_up_email_required": "Email is required",
  "sign_up_password_required": "Password is required",
  "sign_up_password_min_length": "Password must be at least 6 characters",
  "sign_up_success": "User Created",
  "sign_up_error_email_in_use": "This email is already in use! you can't use this email",
  "sign_up_error_invalid_email": "The email address is invalid.",
  "sign_up_error_weak_password": "The password is too weak.",
  "sign_up_error_default": "An error occurred during sign-up."
}
